massgen/__init__.py
massgen/_broadcast_channel.py
massgen/agent_config.py
massgen/cancellation.py
massgen/chat_agent.py
massgen/cli.py
massgen/config_builder.py
massgen/config_validator.py
massgen/coordination_tracker.py
massgen/dspy_paraphraser.py
massgen/execution_trace.py
massgen/litellm_provider.py
massgen/logger_config.py
massgen/logs_analyzer.py
massgen/message_templates.py
massgen/orchestrator.py
massgen/persona_generator.py
massgen/plan_execution.py
massgen/plan_storage.py
massgen/session_exporter.py
massgen/shadow_agent.py
massgen/share.py
massgen/structured_logging.py
massgen/structured_logging_utils.py
massgen/system_message_builder.py
massgen/system_prompt_sections.py
massgen/adapters/__init__.py
massgen/adapters/ag2_adapter.py
massgen/adapters/base.py
massgen/adapters/tests/__init__.py
massgen/adapters/tests/test_ag2_adapter.py
massgen/adapters/tests/test_agent_adapter.py
massgen/adapters/utils/__init__.py
massgen/adapters/utils/ag2_utils.py
massgen/adapters/utils/tests/__init__.py
massgen/adapters/utils/tests/test_ag2_utils.py
massgen/api_params_handler/__init__.py
massgen/api_params_handler/_api_params_handler_base.py
massgen/api_params_handler/_chat_completions_api_params_handler.py
massgen/api_params_handler/_claude_api_params_handler.py
massgen/api_params_handler/_gemini_api_params_handler.py
massgen/api_params_handler/_openai_operator_api_params_handler.py
massgen/api_params_handler/_response_api_params_handler.py
massgen/backend/__init__.py
massgen/backend/_compression_utils.py
massgen/backend/_constants.py
massgen/backend/_context_errors.py
massgen/backend/_streaming_buffer_mixin.py
massgen/backend/azure_openai.py
massgen/backend/base.py
massgen/backend/base_with_custom_tool_and_mcp.py
massgen/backend/capabilities.py
massgen/backend/chat_completions.py
massgen/backend/claude.py
massgen/backend/claude_code.py
massgen/backend/cli_base.py
massgen/backend/external.py
massgen/backend/gemini.py
massgen/backend/gemini_utils.py
massgen/backend/grok.py
massgen-0.1.45.dist-info/licenses/LICENSE
massgen-0.1.45.dist-info/METADATA
massgen-0.1.45.dist-info/WHEEL
massgen-0.1.45.dist-info/entry_points.txt
massgen-0.1.45.dist-info/top_level.txt
massgen-0.1.45.dist-info/RECORD
