Metadata-Version: 2.4
Name: massgen
Version: 0.1.45
Summary: Multi-Agent Scaling System - A powerful framework for collaborative AI
Author-email: MassGen Team <contact@massgen.dev>
License: Apache-2.0
Project-URL: Homepage, https://github.com/Leezekun/MassGen
Project-URL: Repository, https://github.com/Leezekun/MassGen
Project-URL: Bug Reports, https://github.com/Leezekun/MassGen/issues
Project-URL: Source, https://github.com/Leezekun/MassGen
Project-URL: Documentation, https://docs.massgen.ai/en/latest/
Keywords: ai,multi-agent,collaboration,orchestration,llm,claude,gemini,gpt,xai
Classifier: Development Status :: 4 - Beta
Classifier: Intended Audience :: Developers
Classifier: Intended Audience :: Science/Research
Classifier: Operating System :: OS Independent
Classifier: Programming Language :: Python :: 3
Classifier: Programming Language :: Python :: 3.10
Classifier: Programming Language :: Python :: 3.11
Classifier: Topic :: Scientific/Engineering :: Artificial Intelligence
Classifier: Topic :: Software Development :: Libraries :: Python Modules
Requires-Python: >=3.11
License-File: LICENSE
Requires-Dist: datasets==3.2.0
Requires-Dist: openai==2.2.0
Requires-Dist: xai-sdk==1.0.0
Requires-Dist: anthropic>=0.61.0
Requires-Dist: cerebras-cloud-sdk==1.46.0
Requires-Dist: lmstudio==1.4.1
Requires-Dist: wcwidth>=0.2.5
Requires-Dist: google-genai>=1.27.0
Requires-Dist: python-dotenv>=1.0.0
Requires-Dist: PyYAML>=6.0
Requires-Dist: rich==14.1.0
Requires-Dist: questionary>=2.0.0
Requires-Dist: requests>=2.31.0
Requires-Dist: typing-extensions>=4.0.0
Requires-Dist: claude-agent-sdk>=0.1.21
Requires-Dist: loguru>=0.7.0
Requires-Dist: mcp>=1.12.0
Requires-Dist: aiohttp>=3.8.0
Requires-Dist: nest-asyncio>=1.6.0
Requires-Dist: fastmcp>=2.12.3
Requires-Dist: sphinx-rtd-theme>=3.0.2
Requires-Dist: sphinx-book-theme>=1.1.4
Requires-Dist: pillow>=11.3.0
Requires-Dist: ag2>=0.9.10
Requires-Dist: pyautogen>=0.10.0
Requires-Dist: google-cloud-aiplatform>=1.71.1
Requires-Dist: pytest>=8.4.2
Requires-Dist: langchain-openai>=1.0.0
Requires-Dist: langgraph>=1.0.0
Requires-Dist: langchain-core>=1.0.0
Requires-Dist: agentscope>=1.0.6
Requires-Dist: smolagents[litellm]>=1.22.0
Requires-Dist: python-docx>=1.2.0
Requires-Dist: openpyxl>=3.1.5
Requires-Dist: python-pptx>=1.0.2
Requires-Dist: opencv-python>=4.12.0.88
Requires-Dist: pypdf2>=3.0.1
Requires-Dist: mem0ai>=1.0.0
Requires-Dist: reportlab>=4.0.0
Requires-Dist: dspy>=2.4.0
Requires-Dist: textual>=0.47.0
Requires-Dist: litellm>=1.0.0
Requires-Dist: fastapi>=0.109.0
Requires-Dist: uvicorn[standard]>=0.27.0
Provides-Extra: observability
Requires-Dist: logfire>=3.0.0; extra == "observability"
Provides-Extra: dev
Requires-Dist: pytest>=7.0.0; extra == "dev"
Requires-Dist: pytest-cov>=4.0.0; extra == "dev"
Requires-Dist: pytest-asyncio>=0.21.0; extra == "dev"
Requires-Dist: black>=23.0.0; extra == "dev"
Requires-Dist: isort>=5.12.0; extra == "dev"
Requires-Dist: flake8>=6.0.0; extra == "dev"
Requires-Dist: mypy>=1.3.0; extra == "dev"
Requires-Dist: pre-commit>=3.0.0; extra == "dev"
Requires-Dist: bandit>=1.7.0; extra == "dev"
Requires-Dist: autoflake>=2.1.0; extra == "dev"
Requires-Dist: pyupgrade>=3.7.0; extra == "dev"
Provides-Extra: docs
Requires-Dist: sphinx>=7.0.0; extra == "docs"
Requires-Dist: sphinx-rtd-theme>=2.0.0; extra == "docs"
Requires-Dist: sphinx-book-theme>=1.1.0; extra == "docs"
Requires-Dist: myst-parser>=2.0.0; extra == "docs"
Requires-Dist: sphinx-copybutton>=0.5.0; extra == "docs"
Requires-Dist: sphinx-autobuild>=2021.3.14; extra == "docs"
Requires-Dist: sphinxcontrib-mermaid>=0.9.0; extra == "docs"
Requires-Dist: sphinx-autodoc-typehints>=1.24.0; extra == "docs"
Requires-Dist: sphinx-autoapi>=3.0.0; extra == "docs"
Requires-Dist: sphinx-design>=0.5.0; extra == "docs"
Requires-Dist: sphinx-tabs>=3.4.0; extra == "docs"
Requires-Dist: sphinx-togglebutton>=0.3.0; extra == "docs"
Requires-Dist: sphinx-inline-tabs>=2023.4.21; extra == "docs"
Requires-Dist: sphinxcontrib-lunrsearch>=0.4; extra == "docs"
Requires-Dist: sphinx-hoverxref>=1.3.0; extra == "docs"
Provides-Extra: docker
Requires-Dist: docker>=7.0.0; extra == "docker"
Provides-Extra: external
Requires-Dist: ag2>=0.9.10; extra == "external"
Provides-Extra: litellm
Requires-Dist: litellm>=1.0.0; extra == "litellm"
Provides-Extra: all
Requires-Dist: litellm>=1.0.0; extra == "all"
Requires-Dist: logfire>=3.0.0; extra == "all"
Dynamic: license-file
